setup.py
pygal_maps_ch/__init__.py
pygal_maps_ch/ch.cantons.svg
pygal_maps_ch/maps.py
pygal_maps_ch.egg-info/PKG-INFO
pygal_maps_ch.egg-info/SOURCES.txt
pygal_maps_ch.egg-info/dependency_links.txt
pygal_maps_ch.egg-info/entry_points.txt
pygal_maps_ch.egg-info/requires.txt
pygal_maps_ch.egg-info/top_level.txt