Metadata-Version: 1.1
Name: pygal-maps-ch
Version: 1.0.1
Summary: Swiss canton map for pygal
Home-page: http://pygal.org/
Author: Serge droz
Author-email: serge.droz@switch.ch
License: GNU LGPL v3+
Keywords: svg,chart,graph,maps,swiss
Platform: Any
Classifier: Development Status :: 4 - Beta
Classifier: Environment :: Console
Classifier: Intended Audience :: End Users/Desktop
Classifier: License :: OSI Approved :: GNU Lesser General Public License v3 or later (LGPLv3+)
Classifier: Operating System :: OS Independent
Classifier: Programming Language :: Python :: 2
Classifier: Programming Language :: Python :: 3
Classifier: Topic :: Multimedia :: Graphics :: Presentation
Provides: pygal_maps_ch
